google_sheet_mcp/__init__.py
google_sheet_mcp/__main__.py
google_sheet_mcp/mcp_instance.py
google_sheet_mcp/py.typed
google_sheet_mcp/server.py
google_sheet_mcp/tool_schema.py
google_sheet_mcp/tools.py
google_sheet_mcp-0.2.1.dist-info/licenses/LICENSE
google_sheet_mcp-0.2.1.dist-info/METADATA
google_sheet_mcp-0.2.1.dist-info/WHEEL
google_sheet_mcp-0.2.1.dist-info/entry_points.txt
google_sheet_mcp-0.2.1.dist-info/top_level.txt
google_sheet_mcp-0.2.1.dist-info/RECORD
