Metadata-Version: 2.4
Name: google-sheet-mcp
Version: 0.2.1
Summary: Model Context Protocol (MCP) server for Google Sheets integration
Author-email: Your Name <your.email@example.com>
Maintainer-email: Your Name <your.email@example.com>
License: MIT
Project-URL: Homepage, https://github.com/yourusername/mcp-google-sheet
Project-URL: Repository, https://github.com/yourusername/mcp-google-sheet.git
Project-URL: Issues, https://github.com/yourusername/mcp-google-sheet/issues
Project-URL: Documentation, https://github.com/yourusername/mcp-google-sheet#readme
Keywords: mcp,google-sheets,model-context-protocol,ai,llm
Classifier: Development Status :: 3 - Alpha
Classifier: Intended Audience :: Developers
Classifier: License :: OSI Approved :: MIT License
Classifier: Operating System :: OS Independent
Classifier: Programming Language :: Python :: 3
Classifier: Programming Language :: Python :: 3.10
Classifier: Programming Language :: Python :: 3.11
Classifier: Programming Language :: Python :: 3.12
Classifier: Topic :: Software Development :: Libraries :: Python Modules
Classifier: Topic :: Internet :: WWW/HTTP :: Dynamic Content
Classifier: Topic :: Office/Business :: Office Suites
Requires-Python: >=3.10
License-File: LICENSE
Requires-Dist: mcp>=1.0.0
Requires-Dist: python-dotenv>=1.0.1
Requires-Dist: gspread>=5.12.0
Requires-Dist: google-auth>=2.23.0
Requires-Dist: google-auth-oauthlib>=1.1.0
Requires-Dist: google-auth-httplib2>=0.1.1
Provides-Extra: dev
Requires-Dist: pytest>=7.0.0; extra == "dev"
Requires-Dist: pytest-asyncio>=0.21.0; extra == "dev"
Requires-Dist: black>=23.0.0; extra == "dev"
Requires-Dist: isort>=5.12.0; extra == "dev"
Requires-Dist: mypy>=1.5.0; extra == "dev"
Requires-Dist: pre-commit>=3.0.0; extra == "dev"
Dynamic: license-file
